pyplist/XMLParser.py
pyplist/XMLWriter.py
pyplist/__init__.py
pyplist/version.py
pyplist-0.0.5.dist-info/LICENSE
pyplist-0.0.5.dist-info/LICENSE.txt
pyplist-0.0.5.dist-info/METADATA
pyplist-0.0.5.dist-info/WHEEL
pyplist-0.0.5.dist-info/top_level.txt
pyplist-0.0.5.dist-info/RECORD
