Metadata-Version: 2.1
Name: pyplist
Version: 0.0.5
Summary: A package for managing 'Apple PList'-files in XML-format.
Home-page: http://github.com/onescr1pt/plists/
Author: Sri Panyam
Author-email: sri.panyam@gmail.com
Maintainer: One Script
Maintainer-email: yyscript@pm.me
License: UNKNOWN
Platform: UNKNOWN
Classifier: Intended Audience :: Developers
Classifier: License :: OSI Approved :: MIT License
Classifier: Operating System :: OS Independent
License-File: LICENSE
License-File: LICENSE.txt
